collectionfield/__init__.py
collectionfield/converter.py
collectionfield/forms.py
collectionfield/validators.py
collectionfield/models/__init__.py
collectionfield/models/fields.py
collectionfield/models/lookups.py
collectionfield/tests/__init__.py
collectionfield/tests/forms.py
collectionfield/tests/models.py
collectionfield/tests/tests.py
django_2_collectionfield-0.0.4.dist-info/LICENSE
django_2_collectionfield-0.0.4.dist-info/METADATA
django_2_collectionfield-0.0.4.dist-info/WHEEL
django_2_collectionfield-0.0.4.dist-info/top_level.txt
django_2_collectionfield-0.0.4.dist-info/RECORD
